{
  "layout": [
    {
      "h": 18,
      "i": "w01",
      "moved": false,
      "static": false,
      "w": 12,
      "x": 0,
      "y": 0
    }
  ],
  "panelMap": {},
  "title": "Hubble Flows Panel",
  "uploadedGrafana": false,
  "version": "v6",
  "widgets": [
    {
      "bucketCount": 30,
      "bucketWidth": 0,
      "columnUnits": {},
      "contextLinks": {
        "linksData": []
      },
      "customLegendColors": {
        "DROPPED": "#E24D42",
        "AUDIT": "#EAB839",
        "FORWARDED": "#299C46",
        "REDIRECTED": "#705DA0"
      },
      "decimalPrecision": 2,
      "description": "Single panel similar to Hubble flows list.",
      "fillMode": "none",
      "fillSpans": false,
      "id": "w01",
      "isLogScale": false,
      "legendPosition": "bottom",
      "lineInterpolation": "spline",
      "lineStyle": "solid",
      "mergeAllActiveQueries": false,
      "nullZeroValues": "zero",
      "opacity": "1",
      "panelTypes": "table",
      "query": {
        "builder": {
          "queryData": [
            {
              "aggregations": [
                {
                  "metricName": "hubble_flows_processed_total",
                  "reduceTo": "sum",
                  "spaceAggregation": "sum",
                  "temporality": "",
                  "timeAggregation": "rate"
                }
              ],
              "dataSource": "metrics",
              "disabled": false,
              "expression": "A",
              "filter": {
                "expression": "source_namespace like '%%' AND destination_namespace like '%%'"
              },
              "functions": [],
              "groupBy": [
                {
                  "dataType": "string",
                  "id": "verdict--string--tag",
                  "isColumn": false,
                  "isJSON": false,
                  "key": "verdict",
                  "type": "tag"
                },
                {
                  "dataType": "string",
                  "id": "source_namespace--string--tag",
                  "isColumn": false,
                  "isJSON": false,
                  "key": "source_namespace",
                  "type": "tag"
                },
                {
                  "dataType": "string",
                  "id": "destination_namespace--string--tag",
                  "isColumn": false,
                  "isJSON": false,
                  "key": "destination_namespace",
                  "type": "tag"
                },
                {
                  "dataType": "string",
                  "id": "source_pod--string--tag",
                  "isColumn": false,
                  "isJSON": false,
                  "key": "source_pod",
                  "type": "tag"
                },
                {
                  "dataType": "string",
                  "id": "destination_pod--string--tag",
                  "isColumn": false,
                  "isJSON": false,
                  "key": "destination_pod",
                  "type": "tag"
                },
                {
                  "dataType": "string",
                  "id": "traffic_direction--string--tag",
                  "isColumn": false,
                  "isJSON": false,
                  "key": "traffic_direction",
                  "type": "tag"
                }
              ],
              "having": {
                "expression": ""
              },
              "legend": "",
              "limit": null,
              "orderBy": [
                {
                  "columnName": "source_namespace",
                  "order": "asc"
                },
                {
                  "columnName": "destination_namespace",
                  "order": "asc"
                }
              ],
              "queryName": "A",
              "source": "",
              "stepInterval": null
            }
          ],
          "queryFormulas": [],
          "queryTraceOperator": []
        },
        "clickhouse_sql": [
          {
            "disabled": false,
            "legend": "",
            "name": "A",
            "query": ""
          }
        ],
        "id": "q01",
        "promql": [
          {
            "disabled": false,
            "legend": "",
            "name": "A",
            "query": ""
          }
        ],
        "queryType": "builder",
        "unit": ""
      },
      "selectedLogFields": [],
      "selectedTracesFields": [],
      "showPoints": false,
      "softMax": 0,
      "softMin": 0,
      "spanGaps": true,
      "stackedBarChart": false,
      "thresholds": [],
      "timePreferance": "GLOBAL_TIME",
      "title": "Hubble Flows (verdict + source/destination pod + ns sort)",
      "yAxisUnit": "none"
    }
  ],
  "uuid": "a74b7cf7-ffca-45ba-8d09-572ceee2280e"
}
